nano/__init__.py
nano/activation/__init__.py
nano/activation/admin.py
nano/activation/apps.py
nano/activation/forms.py
nano/activation/models.py
nano/activation/signals.py
nano/activation/tests.py
nano/activation/urls.py
nano/activation/views.py
nano/activation/migrations/0001_initial.py
nano/activation/migrations/__init__.py
nano/activation/templates/nano/activation/activated.html
nano/activation/templates/nano/activation/activation_form.html
nano/activation/templates/nano/activation/base.html
nano/badge/__init__.py
nano/badge/admin.py
nano/badge/apps.py
nano/badge/models.py
nano/badge/urls.py
nano/badge/views.py
nano/badge/migrations/0001_initial.py
nano/badge/migrations/__init__.py
nano/badge/templates/show_badge_sum.html
nano/badge/templates/badge/badge_list_frag.html
nano/badge/templatetags/__init__.py
nano/badge/templatetags/badge_tags.py
nano/blog/__init__.py
nano/blog/admin.py
nano/blog/apps.py
nano/blog/models.py
nano/blog/settings.py
nano/blog/tests.py
nano/blog/tools.py
nano/blog/urls.py
nano/blog/views.py
nano/blog/migrations/0001_initial.py
nano/blog/migrations/__init__.py
nano/blog/templates/blog/entry_archive.html
nano/blog/templates/blog/entry_archive_day.html
nano/blog/templates/blog/entry_archive_month.html
nano/blog/templates/blog/entry_archive_year.html
nano/blog/templates/blog/entry_list.html
nano/blog/templates/blog/entry_with_day.html
nano/blog/templates/blog/entry_with_fulldate.html
nano/blog/templates/blog/entry_with_fulldatetime.html
nano/blog/templates/blog/entry_with_monthday.html
nano/blog/templates/blog/entry_with_time.html
nano/blog/templates/blog/new_user.html
nano/chunk/__init__.py
nano/chunk/admin.py
nano/chunk/apps.py
nano/chunk/loader.py
nano/chunk/loaders.py
nano/chunk/models.py
nano/chunk/tests.py
nano/chunk/migrations/0001_initial.py
nano/chunk/migrations/__init__.py
nano/comments/__init__.py
nano/comments/admin.py
nano/comments/apps.py
nano/comments/forms.py
nano-0.10.0.dist-info/DESCRIPTION.rst
nano-0.10.0.dist-info/METADATA
nano-0.10.0.dist-info/RECORD
nano-0.10.0.dist-info/WHEEL
nano-0.10.0.dist-info/metadata.json
nano-0.10.0.dist-info/top_level.txt
